{
    "images": [
        {
            "url": "https://cms.volaris.com/globalassets/new-content-pages/servicios-especiales/animales-de-servicio/perro-de-servicio-m.9.png",
            "date": "12/12/2020",
            "category": "Cultura",
            "author": "jose123"
        },
        {
            "url": "http://c.files.bbci.co.uk/48DD/production/_107435681_perro1.jpg",
            "date": "08/09/2021",
            "category": "Deportes",
            "author": "jose123"
        },
        {
            "url": "http://c.files.bbci.co.uk/48DD/production/_107435681_perro1.jpg",
            "date": "12/06/2021",
            "category": "Niños",
            "author": "pedrito123"
        },
        {
            "url": "https://dam.ngenespanol.com/wp-content/uploads/2019/10/perros-personalidad-2.jpg",
            "date": "29/10/2021",
            "category": "Educación",
            "author": "pedrito123"
        },
        {
            "url": "https://dam.ngenespanol.com/wp-content/uploads/2019/10/perros-personalidad-2.jpg",
            "date": "19/01/2021",
            "category": "Libros",
            "author": "jose123"
        }
    ],
    "videos": [
        {
            "url": "https://www.youtube.com/watch?v=dHN8WqHDklM",
            "date": "23/09/2021",
            "category": "Cultura",
            "author": "pedrito123"
        },
        {
            "url": "https://www.youtube.com/watch?v=rsTLyukvxGU",
            "date": "22/07/2021",
            "category": "Internacional",
            "author": "pedrito123"
        },
        {
            "url": "https://www.youtube.com/watch?v=rsTLyukvxGU",
            "date": "23/03/2021",
            "category": "Educación",
            "author": "pedrito123"
        },
        {
            "url": "https://www.youtube.com/watch?v=rsTLyukvxGU",
            "date": "13/07/2021",
            "category": "Actualidad",
            "author": "jose123"
        },
        {
            "url": "https://www.youtube.com/watch?v=dHN8WqHDklM",
            "date": "01/04/2021",
            "category": "Actualidad",
            "author": "pedrito123"
        }
    ]
}